neuralflow/__init__.py
neuralflow/config.py
neuralflow/data.py
neuralflow/function.py
neuralflow/function_class.py
neuralflow/gpu.py
neuralflow/model.py
neuralflow/optimizer.py
neuralflow/trainer.py
neuralflow/utils.py
neuralflow/cv/__init__.py
neuralflow/cv/model.py
neuralflow/epoch_notice/__init__.py
neuralflow/epoch_notice/email.py
neuralflow/nlp/__init__.py
neuralflow/nlp/model.py
neuralflow/nlp/utils.py
neuralflow-1.0.1.dist-info/LICENSE
neuralflow-1.0.1.dist-info/METADATA
neuralflow-1.0.1.dist-info/WHEEL
neuralflow-1.0.1.dist-info/top_level.txt
neuralflow-1.0.1.dist-info/RECORD
