Metadata-Version: 2.1
Name: neuralflow
Version: 1.0.1
Summary: Deep learning framework built with numpy (cupy)
Home-page: https://github.com/augustinLib/neuralflow
Author: Sangam Lee
Author-email: 2bhambitious@gmail.com
License: MIT
Classifier: Programming Language :: Python :: 3
Classifier: License :: OSI Approved :: MIT License
Classifier: Operating System :: OS Independent
Requires-Python: >=3.8
License-File: LICENSE
Requires-Dist: cupy-cuda11x (==11.5.0)
Requires-Dist: matplotlib (==3.6.3)
Requires-Dist: matplotlib-inline (==0.1.6)
Requires-Dist: numpy (==1.24.1)
Requires-Dist: packaging (==23.0)
Requires-Dist: pandas (==1.5.3)
Requires-Dist: pickleshare (==0.7.5)
Requires-Dist: Pillow (==9.4.0)
Requires-Dist: tqdm (==4.64.1)
